CHANGELOG.rst
LICENSE
MANIFEST.in
Makefile
NOTICE.txt
README.rst
requirements.txt
setup.py
tests-requirements.txt
tox.ini
perf8/__init__.py
perf8/cli.py
perf8/logger.py
perf8/reporter.py
perf8/runner.py
perf8/watcher.py
perf8.egg-info/PKG-INFO
perf8.egg-info/SOURCES.txt
perf8.egg-info/dependency_links.txt
perf8.egg-info/entry_points.txt
perf8.egg-info/not-zip-safe
perf8.egg-info/requires.txt
perf8.egg-info/top_level.txt
perf8/plugins/__init__.py
perf8/plugins/_asyncstats.py
perf8/plugins/_cprofile.py
perf8/plugins/_memray.py
perf8/plugins/_psutil.py
perf8/plugins/_pyspy.py
perf8/plugins/base.py
perf8/speedscope/demangle-cpp.1768f4cc.js
perf8/speedscope/demangle-cpp.1768f4cc.js.map
perf8/speedscope/favicon-16x16.f74b3187.png
perf8/speedscope/favicon-32x32.bc503437.png
perf8/speedscope/file-format-schema.json
perf8/speedscope/import.a03bf119.js
perf8/speedscope/import.a03bf119.js.map
perf8/speedscope/index.html
perf8/speedscope/perf-vertx-stacks-01-collapsed-all.2681da68.txt
perf8/speedscope/release.txt
perf8/speedscope/reset.8c46b7a1.css
perf8/speedscope/reset.8c46b7a1.css.map
perf8/speedscope/source-map.438fa06b.js
perf8/speedscope/source-map.438fa06b.js.map
perf8/speedscope/speedscope.eee21de6.js
perf8/speedscope/speedscope.eee21de6.js.map
perf8/templates/base.html
perf8/templates/index.html
perf8/tests/__init__.py
perf8/tests/ademo.py
perf8/tests/demo.py
perf8/tests/test_cli.py
perf8/tests/test_watcher.py