Metadata-Version: 2.1
Name: perf8
Version: 0.0.1
Summary: Your Tool For Python Performance Tracking
Home-page: https://github.com/elastic/perf8
Author: Ingestion Team
Author-email: tarek@ziade.org
Classifier: Programming Language :: Python
Classifier: License :: OSI Approved :: Apache Software License
Classifier: Development Status :: 5 - Production/Stable
Classifier: Programming Language :: Python :: 3 :: Only
Classifier: Programming Language :: Python :: 3.9
Classifier: Programming Language :: Python :: 3.10
Classifier: Programming Language :: Python :: 3.11
License-File: LICENSE
License-File: NOTICE.txt
